pybud/ConsoleLogger.py
pybud/DiffFinder.py
pybud/PyBud.py
pybud/__init__.py
pybud/__main__.py
pybud/example.py
pybud/json_helper.py
pybud/main.py
pybud/printout_builders.py
pybud/utils.py
pybud/tests/__init__.py
pybud/tests/knapsack.py
pybud/tests/perform_tests.py
pybud/tests/search_algos.py
pybud/tests/sort_algos.py
pybud/video/VideoLogger.py
pybud/video/__init__.py
pybud/video/encoders.py
pybud/video/video_config_handler.py
pybud-0.2.3.dist-info/LICENSE.md
pybud-0.2.3.dist-info/METADATA
pybud-0.2.3.dist-info/WHEEL
pybud-0.2.3.dist-info/entry_points.txt
pybud-0.2.3.dist-info/top_level.txt
pybud-0.2.3.dist-info/RECORD
