Metadata-Version: 2.1
Name: pybud
Version: 0.2.3
Summary: A Python tool that generates video visualizations for source code debugging.
Home-page: https://github.com/CCExtractor/PyBud
Author: Eastan Giebler
Author-email: kupa528@yahoo.com
License: MIT
Download-URL: https://github.com/CCExtractor/PyBud/archive/v0.2.3.tar.gz
Keywords: debugger,tool,python,video
Platform: UNKNOWN
Classifier: Development Status :: 4 - Beta
Classifier: License :: OSI Approved :: MIT License
Classifier: Operating System :: OS Independent
Classifier: Programming Language :: Python :: 3
Classifier: Programming Language :: Python :: 3.6
Classifier: Programming Language :: Python :: 3.7
Classifier: Programming Language :: Python :: 3.8
Requires-Python: >=3.6
Requires-Dist: dictdiffer (==0.8.1)
Requires-Dist: Pillow (==7.0.0)
Requires-Dist: opencv-python
Requires-Dist: numpy
Requires-Dist: pyyaml
